{
  "annotations": {
    "changelogDate": "20240120015124"
  },
  "applications": "*",
  "entityTableName": "categoria_produto",
  "fields": [
    {
      "fieldName": "nome",
      "fieldType": "String",
      "fieldValidateRules": ["required"]
    },
    {
      "fieldName": "descricao",
      "fieldType": "String"
    }
  ],
  "jpaMetamodelFiltering": true,
  "name": "CategoriaProduto",
  "pagination": "infinite-scroll",
  "relationships": [],
  "searchEngine": "no",
  "service": "serviceImpl"
}
